Workbook

Sheet Income Statement-Robi
D4: Robi Axiata PLC - Income Statement
D7: Particulars | E7: 2025 | F7: 2024 | G7: 2023 | H7: 2022 | I7: 2021 | J7: 2020
D9: Revenue | E9: 99922095000 | F9: 99502359000 | G9: 99422639000 | H9: 85859740000 | I9: 81424640000 | J9: 75642696000
D10: Costs of Sales/ Cost of material and traffic charges | E10: 61269089000 | F10: 58126946000 | G10: 60960393000 | H10: 53523042000 | I10: 53988125000 | J10: 47358401000
D11: Gross Profit | E11: 36306006000 | F11: 41375413000 | G11: 38461706000 | H11: 32366998000 | I11: 27436150000 | J11: 28284295000
D12: Distribution expenses | E12: 11292438000 | F12: 13326319000 | G12: 14095350000 | H12: 12862911000 | I12: 12389783000 | J12: 11456885000
D13: Administrative expenses | E13: 5607495000 | F13: 4659228000 | G13: 4535682000 | H13: 3332784000 | I13: 3453140000 | J13: 3398000000
D14: Operation and maintenance | E14: 2909040000 | F14: 1544425000 | G14: 2611579000 | H14: 2528521000 | I14: 2335954000 | J14: 2903385000
D15: Operating Profit/ (loss) | E15: 18824033000 | F15: 21845441000 | G15: 17219095000 | H15: 13512482000 | I15: 9257639000 | J15: 10526025000
D16: Employee benefits expenses | E16: 580520000 | F16: 689946000 | G16: 455212000 | H16: 235941000 | I16: 253334000 | J16: 276334000
D17: Non-Operating Income | E17: 76056000 | F17: 335651000 | G17: 278994000 | H17: 185380000 | I17: 203042000 | J17: 146088000
D18: Finance Expenses | E18: 6955017000 | F18: 7251744000 | G18: 6350684000 | H18: 5857490000 | I18: 4017381000 | J18: 4888850000
D19: Foreign Exchange gain | J19: 1677000
D20: Foreign Exchange Loss | E20: 54331000 | F20: 732921000 | G20: 1654088000 | H20: 2976716000 | I20: 224878000
D21: Profit / (Loss) Before Tax | E21: 11310221000 | F21: 13506521000 | G21: 9038005000 | H21: 4627715000 | I21: 4965088000 | J21: 5508606000
D22: Income Tax Expense | E22: 1939399000 | F22: 6478724000 | G22: 5828407000 | H22: 2800516000 | I22: 3158761000 | J22: 3955291000
D23: Profit / (loss) for the Period | E23: 9370822000 | F23: 7027797000 | G23: 3209598000 | H23: 1827199000 | I23: 1806327000 | J23: 1553315000
D24: EPS | E24: 1.79 | F24: 1.34 | G24: 0.61 | H24: 0.35 | I24: 0.34 | J24: 0.33

Sheet Balance Sheet-Robi
C4: Robi Axiata PLC - Balance Sheet
C7: Particulars | D7: 2025 | E7: 2024 | F7: 2023 | G7: 2022 | H7: 2021 | I7: 2020
C9: Property Plant & Equipment | D9: 108539701000 | E9: 113838335000 | F9: 111851614000 | G9: 108852659000 | H9: 109450354000 | I9: 107044991000
C10: Intangible Assets | D10: 35286075000 | E10: 39618960000 | F10: 48213887000 | G10: 36076067000 | H10: 42948690000 | I10: 39841489000
C11: Investments in Associates | D11: 123914000 | E11: 203705000
C12: Right-of-use assets | D12: 43272049000 | E12: 34352968000 | F12: 39551073000 | G12: 31444653000 | H12: 32197773000 | I12: 27855249000
C13: Other non-current assets | D13: 2658120000 | E13: 2051743000 | F13: 3422432000 | G13: 3419827000 | H13: 3419827000 | I13: 4134113000
C14: Deferred Tax Assets | G14: 3211038000 | H14: 3942222000 | I14: 1052277000
C15: Total Non Current Assets | D15: 189879859000 | E15: 190065711000 | F15: 203039006000 | G15: 183004244000 | H15: 191958866000 | I15: 179928119000
C16: Inventory | D16: 352832000 | E16: 337027000 | F16: 495282000 | G16: 503914000 | H16: 350814000 | I16: 155881000
C17: Trade & other receivables | D17: 8399445000 | E17: 8110998000 | F17: 7709877000 | G17: 7383411000 | H17: 8146611000 | I17: 7365644000
C18: Short term investments | D18: 223249000 | E18: 388130000 | F18: 379700000 | G18: 373452000 | H18: 389848000 | I18: 383008000
C19: Cash & cash equivalents | D19: 2421440000 | E19: 2618657000 | F19: 3535725000 | G19: 3563406000 | H19: 4918491000 | I19: 9469879000
C20: Advance, deposits & prepayments | D20: 4634242000 | E20: 5432211000 | F20: 3277972000 | G20: 4725653000 | H20: 1849736000 | I20: 2182327000
C21: Employee benefits | D21: 75758000 | E21: 219373000 | F21: 566095000 | G21: 191006000
C22: Total Current Assets | D22: 16106966000 | E22: 17106396000 | F22: 15964651000 | G22: 16740842000 | H22: 15635500000 | I22: 19536739000
C23: Total Assets | D23: 205986825000 | E23: 207172107000 | F23: 219003657000 | G23: 199745086000 | H23: 207594366000 | I23: 199464858000
C24: Stated capital | D24: 52379329000 | E24: 52379329000 | F24: 52379329000 | G24: 52379329000 | H24: 52379329000 | I24: 52379329000
C25: Retained Earnings | D25: 10813827000 | E25: 9463294000 | F25: 7774186000 | G25: 8084815000 | H25: 7165837000 | I25: 6914405000
C26: Reserves | D26: 6662397000 | E26: 6662397000 | F26: 6662397000 | G26: 6662397000 | H26: 6662397000 | I26: 6662397000
C27: Total Equity | D27: 69855553000 | E27: 68505020000 | F27: 66815912000 | G27: 67126541000 | H27: 66207563000 | I27: 65956131000
C28: Interest Bearing Borrowings to related parties | F28: 7641195000 | G28: 10085541000 | H28: 8079635000 | I28: 10353244000
C29: Deferred Tax Liabilities | D29: 3235517000 | E29: 5130295000 | F29: 437886000
C30: Reimbursement Benefit Obligations / Employee Benefits | H30: 20155000 | I30: 361702000
C31: Asset retirement obligation | D31: 169153000 | E31: 168549000 | F31: 526988000 | G31: 479416000 | H31: 557833000 | I31: 405099000
C32: Accounts Payable-Non Current Liabilities | D32: 16473650000 | E32: 16368111000 | F32: 22469332000 | G32: 8968041000 | H32: 14435881000 | I32: 12199599000
C33: Obligation under finances & operating leases | D33: 46048819000 | E33: 36171842000 | F33: 41595299000 | G33: 36968382000 | H33: 37273308000 | I33: 32497180000
C34: Other non-current liabilities | D34: 5128345000 | E34: 5128345000 | F34: 3937312000 | G34: 4148011000 | H34: 4717328000 | I34: 3891548000
C35: Total Non Current Liabilities | D35: 71055484000 | E35: 62967142000 | F35: 76607592000 | G35: 60649391000 | H35: 65084140000 | I35: 59708372000
C36: Trade & other payables / Sundry Creditors | D36: 49977847000 | E36: 50076833000 | F36: 54394327000 | G36: 52220381000 | H36: 54670164000 | I36: 52117136000
C37: Lease liabilities | D37: 3288983000 | E37: 6679753000 | F37: 4316194000 | G37: 2852904000 | H37: 2480806000 | I37: 1919578000
C38: IPO refund warrant Liabilities | I38: 106284000
C39: Short term loans | D39: 20028000 | E39: 7700399000 | F39: 3849898000 | G39: 3738585000 | H39: 8094752000 | I39: 11543889000
C40: Interest bearing term loans | E40: 1997792000 | F40: 2987545000 | G40: 3568645000 | H40: 1702242000 | I40: 2439961000
C41: Deposit against employee share purchase plan (ESPP) | I41: 65274000
C42: Tax & VAT payable | D42: 11713428000 | E42: 9185958000 | F42: 9972861000 | G42: 9558625000 | H42: 9342585000 | I42: 5608233000
C43: Unclaimed Dividend | D43: 75502000 | E43: 59210000 | F43: 59108000 | G43: 30014000 | H43: 12114000
C44: Total Current Liabilities | D44: 65075788000 | E44: 75699945000 | F44: 75759753000 | G44: 71969154000 | H44: 76302663000 | I44: 73800355000
C45: Total Owners Equity & Liabilities | D45: 205986825000 | E45: 207172107000 | F45: 219003657000 | G45: 199745086000 | H45: 207594366000 | I45: 199464858000
C46: Book Value Per Share | D46: 13.34 | E46: 13.08 | F46: 12.76 | G46: 12.82 | H46: 12.64 | I46: 13.9

Sheet Cash Flow-Robi
C5: Robi Axiata PLC - Cash Flow Statement
C8: Particulars | D8: 2025 | E8: 2024 | F8: 2023 | G8: 2022 | H8: 2021 | I8: 2020
C10: Cash received from customers | D10: 134473768000 | E10: 132291747000 | F10: 121414932000 | G10: 105212318000 | H10: 97790015000 | I10: 89794815000
C11: Payment to suppliers, employees and others | D11: -39145477000 | E11: -38883399000 | F11: -39072081000 | G11: -35536161000 | H11: -34489246000 | I11: -39137322000
C12: Income tax paid | D12: -47992105000 | E12: -47176865000 | F12: -41542193000 | G12: -32401636000 | H12: -30740189000 | I12: -25199040000
C13: Net Cash Generated from Operating Activities | D13: 47336186000 | E13: 46231483000 | F13: 40800658000 | G13: 37274521000 | H13: 32560580000 | I13: 25458453000
C14: Purchase of Property, Plant & Equipment | D14: -16708368000 | E14: -28377516000 | F14: -23998443000 | G14: -28437012000 | H14: -23940283000 | I14: -21184349000
C15: Proceeds on Sale of Property, Plant & Equipment | D15: 17980000 | E15: 87746000 | F15: 57421000 | G15: 82178000 | H15: 12650000 | I15: 45187000
C16: Interest and insurance claim received | D16: 145106000 | E16: 93949000 | F16: 218163000 | G16: 91558000 | H16: 120271000 | I16: 108399000
C17: Net Cash Flow from Investing Activities | D17: -16545282000 | E17: -28195821000 | F17: -23722859000 | G17: -28263276000 | H17: -23807362000 | I17: -21030763000
C18: Proceeds from Loans | D18: 22590790000 | E18: 25864000000 | F18: 9002000000 | G18: 18234000000 | H18: 31368551000 | I18: 44972955000
C19: Lease Repayment/Payment of financial lease obligation | D19: -33308664000 | E19: -32580733000 | F19: -14087626000 | G19: -21276897000 | H19: -38389648000 | I19: -43542030000
C20: Deposit against ESPP including interest* | I20: 65002000
C21: Proceeds from share issuance including offer subscription | I21: 3987452000
C22: Payment of dividend | D22: -7842180000 | E22: -4461803000 | F22: -4310863000 | G22: -1039130000 | H22: -364602000
C23: Payment of finance lease obligation | D23: -12427718000 | E23: -7810785000 | F23: -7762222000 | G23: -6286555000 | H23: -5812917000 | I23: -4958216000
C24: Repayment of IPO refund liability | H24: -105899000
C25: Net Cash Flow from Financing Activities | D25: -30987772000 | E25: -18989121000 | F25: -17158711000 | G25: -10368583000 | H25: -13304515000 | I25: 525163000
C26: Net change in cash and cash equivalents | D26: -196868000 | E26: -953459000 | F26: -80912000 | G26: -1357336000 | H26: -4551297000 | I26: 4952853000
C27: Effect of exchange rate fluctuation on cash held | D27: -349000 | E27: 36390000 | F27: 53231000 | G27: 2253000 | H27: -91000
C28: Cash at the beginning of the period | D28: 2618657000 | E28: 3535725000 | F28: 3563406000 | G28: 4918491000 | H28: 9469879000 | I28: 4517026000
C29: Cash at the end of the period | D29: 2421440000 | E29: 2618657000 | F29: 3535725000 | G29: 3563406000 | H29: 4918491000 | I29: 9469879000
C30: NOCFPS | D30: 9.04 | E30: 8.83 | F30: 7.79 | G30: 7.12 | H30: 6.22 | I30: 5.36

Sheet Cost of Debt
C6: Cost of Debt
C8: Particulars | D8: 2025 | E8: 2024 | F8: 2023 | G8: 2022 | H8: 2021 | I8: 2020
C10: Cash | D10: 2421440000 | E10: 2618657000 | F10: 3535725000 | G10: 3563406000 | H10: 4918491000 | I10: 9469879000
C11: ST investment | D11: 223249000 | E11: 388130000 | F11: 379700000 | G11: 373452000 | H11: 389848000 | I11: 383008000
C12: Total Liquid asset | D12: =D10+D11 -> 2644689000 | E12: =E10+E11 -> 3006787000 | F12: =F10+F11 -> 3915425000 | G12: =G10+G11 -> 3936858000 | H12: =H10+H11 -> 5308339000 | I12: =I10+I11 -> 9852887000
C13: ST Debt
C14: LT Debt
C15: Total debt | D15: 136131272000 | E15: 138667087000 | F15: 152187745000 | G15: 132618545000 | H15: 141386803000 | I15: 133508727000
C16: Net Debt | D16: =-(D12-D15) -> 133486583000 | E16: =-(E12-E15) -> 135660300000 | F16: =-(F12-F15) -> 148272320000 | G16: =-(G12-G15) -> 128681687000 | H16: =-(H12-H15) -> 136078464000 | I16: =-(I12-I15) -> 123655840000 | K16: Assumption: set to 0 (operating FMCG business, not a financing company)
C17: Interest Income | D17: 0 | E17: 0 | F17: 0 | G17: 0 | H17: 0 | I17: 0
C18: Interest Expense | D18: 6955017000 | E18: 7251744000 | F18: 6350684000 | G18: 5857490000 | H18: 4017381000 | I18: 4888850000
C19: Net Interest | D19: =D18-D17 -> 6955017000 | E19: =E18-E17 -> 7251744000 | F19: =F18-F17 -> 6350684000 | G19: =G18-G17 -> 5857490000 | H19: =H18-H17 -> 4017381000 | I19: =I18-I17 -> 4888850000
C20: Implied cost of debt | E20: 0.0085104426 | F20: 0.0018093462 | G20: 0.0037624867 | H20: 0.0038694627 | I20: 0.017835308
C22: Interest rate earned | E22: 0 | F22: 0 | G22: 0 | H22: 0 | I22: 0
C23: Interest rate paid | E23: 0.21054976 | F23: 0.010973537 | G23: 0.034313065 | H23: 0.27480895 | I23: 0.45865165
C27: Implied cost of debt | E27: 0.0085104426 | F27: 0.0018093462 | G27: 0.0037624867 | H27: 0.0038694627 | I27: 0.017835308 | K27: =AVERAGE(E27:I27) -> 0.0071574093

Sheet Cost of Equity
D4: Cost of Equity & WACC | Q4: Market Cap | R4: 156090.4
D5: Current Share price, Po | E5: 29.8 | I5: Year | J5: 2020 | K5: 2021 | L5: 2022 | M5: 2023 | N5: 2024 | O5: 2025 | Q5: Tax Rate | R5: 0.17
D6: Current Dividend, Divo | E6: =AVERAGE(J6:O6) -> 0.0915 | F6: Average of 6 yrs dividend per share | I6: DPS (Taka/share) | J6: 0 | K6: 0.05 | L6: 0.07 | M6: 0.104 | N6: 0.15 | O6: 0.175 | Q6: Firm Value | R6: =('Cost of Debt'!D16/1000000)+'Cost of Equity'!R4 -> 289576.98
D7: Growth Rate, g | E7: =AVERAGE(E31:I31) -> 0.49080409 | F7: Avg. historical YoY NPAT growth (2020-2025) | I7: Payout ratio | J7: =J6/'Income Statement-Robi'!E24 -> 0 | K7: =K6/'Income Statement-Robi'!F24 -> 0.037313433 | L7: =L6/'Income Statement-Robi'!G24 -> 0.1147541 | M7: =M6/'Income Statement-Robi'!H24 -> 0.29714286 | N7: =N6/'Income Statement-Robi'!I24 -> 0.44117647 | O7: =O6/'Income Statement-Robi'!J24 -> 0.53030303
D8: COE | E8: =E6*(1+E7)/E5+E7 -> 0.49538156
Q9: Total Dividend 2025 | R9: 9166983575
G10: Avg. payout | H10: =AVERAGE(J7:O7) -> 0.23678165
G11: Retention | H11: =1-H10 -> 0.76321835
G12: ROE | H12: ='Income Statement-Robi'!E23/'Balance Sheet-Robi'!D27 -> 0.1341457
D13: WACC | E13: =(R4/R6)*E8+(('Cost of Equity'!F16/1000000)/'Cost of Equity'!R6)*'Cost of Equity'!F17*(1-'Cost of Equity'!R5) -> 0.26976351
D15: Total Dividend (base year, implied) | E15: =E6*9166983575 -> 8.38779e+08
E16: Net Debt (2025) | F16: 133486583000
E17: COD | F17: 0.0071574093
D29: YoY growth for each year | E29: 2025 | F29: 2024 | G29: 2023 | H29: 2022 | I29: 2021 | J29: 2020
D30: Profit / (loss) for the Period | E30: 9370822000 | F30: 7027797000 | G30: 3209598000 | H30: 1827199000 | I30: 1806327000 | J30: 1553315000
E31: =(E30/F30)-1 -> 0.33339395 | F31: =(F30/G30)-1 -> 1.1896191 | G31: =(G30/H30)-1 -> 0.75656729 | H31: =(H30/I30)-1 -> 0.01155494 | I31: =(I30/J30)-1 -> 0.16288518 | J31: 0
D33: Div1 | E33: =E6*(1+E7) -> 0.13640857
E34: =E33/E5 -> 0.0045774689

Sheet TAX
C2: Effective Tax Rate
C4: Particulars | D4: 2025 | E4: 2024 | F4: 2023 | G4: 2022 | H4: 2021 | I4: 2020
C5: Profit Before Tax | D5: 11310221000 | E5: 13506521000 | F5: 9038005000 | G5: 4627715000 | H5: 4965088000 | I5: 5508606000
C6: Income Tax Expenses | D6: 1939399000 | E6: 6478724000 | F6: 5828407000 | G6: 2800516000 | H6: 3158761000 | I6: 3955291000
C7: Tax rate | D7: =D6/D5 -> 0.17147313 | E7: =E6/E5 -> 0.47967378 | F7: =F6/F5 -> 0.6448776 | G7: =G6/G5 -> 0.60516173 | H7: =H6/H5 -> 0.63619436 | I7: =I6/I5 -> 0.71802031

Sheet FCF
C2: Free Cash Flow (base year 2025)
C4: Particulars | D4: 2025
C5: Cash received from customers | D5: 134473768000
C6: Payment to suppliers, employees and others | D6: -39145477000
C7: Income tax paid | D7: -47992105000
C8: Net Cash Generated from Operating Activities | D8: 47336186000
C9: Purchase of Property, Plant & Equipment | D9: -16708368000
C10: Proceeds on Sale of Property, Plant & Equipment | D10: 17980000
C11: Interest and insurance claim received | D11: 145106000
C12: Net Cash Flow from Investing Activities | D12: -16545282000
C13: Free cash flow before interest adjustment | D13: =D8+D12 -> 30790904000
C14: Add back after-tax net interest | D14: 4173010200
C15: Free cash flow (FCF) | D15: =D13+D14 -> 34963914200

Sheet CFFA
B3: FCF & CFFA Valuation
B4: EBIT (2025) | C4: 18824033 | D4: 2025 base year | E4: OCF (calc.) | F4: =C4*(1-C6)+C5 -> 46627461 | G4: CFFA | H4: =F4-F5-F6 -> 6156836.3 | I4: FCF | J4: =FCF!D15 -> 34963914200
B5: Depreciation | C5: 31031750 | E5: NWC | F5: =(C7-C8)-(C9-C10) -> 9624727 | G5: Perpetual growth rate | H5: 0.005
B6: Tax rate | C6: 0.1715 | E6: CAPEX (NCS) | F6: =C11-C12+C5 -> 30845898 | G6: WACC | H6: ='Cost of Equity'!E13 -> 0.26976351 | J6: Terminal | K6: =(H4*(1+H5))/(H6-H5) -> 23370368
B7: Current Assets 2025 | C7: 16106966 | G7: Growth (6-yr explicit) | H7: 0.3
B8: Current Liabilities 2025 | C8: 65075788
B9: Current Assets 2024 | C9: 17106396
B10: Current Liabilities 2024 | C10: 75699945
B11: Total Non-Current Assets 2025 | C11: 189879859
B12: Total Non-Current Assets 2024 | C12: 190065711 | H12: 1 | I12: 2 | J12: 3 | K12: 4 | L12: 5 | M12: 6
G13: Year | H13: 2025 | I13: 2026 | J13: 2027 | K13: 2028 | L13: 2029 | M13: 2030
G14: FCF | H14: =J4 -> 34963914200 | I14: =H14*(1+$H$7) -> 45453088460 | J14: =I14*(1+$H$7) -> 59089014998 | K14: =J14*(1+$H$7) -> 7.6815719e+10 | L14: =K14*(1+$H$7) -> 9.9860435e+10 | M14: =L14*(1+$H$5)^M12 -> 1.0289395e+11
G15: Terminal Value | M15: =M14*(1+H5)/(H6-H5) -> 3.9056899e+11
G16: Total CF | H16: =H14 -> 34963914200 | I16: =I14 -> 45453088460 | J16: =J14 -> 59089014998 | K16: =K14 -> 7.6815719e+10 | L16: =L14+M15 -> 4.9042943e+11
G17: Enterprise Value | H17: =NPV(H6,H16:L16) -> 2.6272078e+11 | I17: Cash & equivalents | J17: 2421440000 | K17: Financial liabilities | L17: 136131272000
G18: Equity Value | H18: =H17+J17-L17 -> 1.2901095e+11
G20: Stock price | H20: =H18/5237932895 -> 24.630126
H25: number of stocks- | I25: 5,23,79,32,895

Sheet FCFF & FCFE
A1: FCFF and FCFE
A2: 2025 Base year | D2: 2024 Base year
A3: CFO | B3: =FCF!D8 -> 47336186000 | D3: Net debt issued | E3: ='Cash Flow-Robi'!E18+'Cash Flow-Robi'!E23+'Cash Flow-Robi'!E19 -> -14527518000 | F3: *Neg means Robi repaid more debt that it raised in 2025
A4: Income tax expense | B4: =TAX!D6 -> 1939399000 | D4: Cash From Operations | E4: 46231480000
A5: Tax rate | B5: =TAX!D7 -> 0.17147313
A6: Cash Capex | B6: 30845898000
A8: FCFF | B8: =B3+'Income Statement-Robi'!E18*(1-B5)-D12 -> 5.3098604e+10 | D8: FCFE | E8: =E4-D12+E3 -> 31703962000

Sheet FCFF Valuation
C4: FCFF Valuation
C5: FCFF | D5: ='FCFF & FCFE'!B8 -> 5.3098604e+10
C6: Perpetual growth rate | D6: 0.005
C7: WACC | D7: =CFFA!H6 -> 0.26976351
C8: Growth (6-yr explicit) | D8: =CFFA!H7 -> 0.3
C9: Total Shares | D9: 5237932895
E11: 1 | F11: 2 | G11: 3 | H11: 4 | I11: 5 | J11: 6
D12: Year | E12: 2025 | F12: 2026 | G12: 2027 | H12: 2028 | I12: 2029 | J12: 2030
D13: FCFF | E13: =$D$5*(1+$D$8)^E11 -> 6.9028186e+10 | F13: =$D$5*(1+$D$8)^F11 -> 8.9736642e+10 | G13: =$D$5*(1+$D$8)^G11 -> 1.1665763e+11 | H13: =$D$5*(1+$D$8)^H11 -> 1.5165492e+11 | I13: =$D$5*(1+$D$8)^I11 -> 1.971514e+11 | J13: =$D$5*(1+$D$8)^J11 -> 2.5629682e+11
D14: Terminal Value | J14: =J13/(D7-D6) -> 9.6802171e+11
D15: Total CF | E15: =E13 -> 6.9028186e+10 | F15: =F13 -> 8.9736642e+10 | G15: =G13 -> 1.1665763e+11 | H15: =H13 -> 1.5165492e+11 | I15: =I13+J14 -> 1.1651731e+12
D16: Enterprise Value | E16: =NPV(D7,E15:I15)*(1+D7)^0.5 -> 6.5170055e+11
D18: Cash & equivalents | E18: ='[1]Balance Sheet'!D19 -> 130000000
D19: Financial liabilities | E19: ='[1]Cost of Debt'!D11 -> 21629000
D20: Equity Value | E20: =E16+E18-E19 -> 6.5180892e+11
D21: Stock Price | E21: =E20/D9 -> 124.44011

Sheet FCFE Valuation
C3: FCFE Valuation
C4: FCFE | D4: ='FCFF & FCFE'!E8 -> 31703962000
C5: Perpetual growth rate | D5: 0.005
C6: COE | D6: ='Cost of Equity'!E8 -> 0.49538156
C7: Growth | D7: ='Cost of Equity'!E7 -> 0.49080409
C8: Total Shares | D8: 5237932895
E10: 1 | F10: 2 | G10: 3 | H10: 4 | I10: 5 | J10: 6
D11: Year | E11: 2025 | F11: 2026 | G11: 2027 | H11: 2028 | I11: 2029 | J11: 2030
D12: FCFE | E12: =$D$4*(1+$D$7)^E10 -> 4.7264396e+10 | F12: =$D$4*(1+$D$7)^F10 -> 7.0461955e+10 | G12: =$D$4*(1+$D$7)^G10 -> 1.0504497e+11 | H12: =$D$4*(1+$D$7)^H10 -> 1.5660147e+11 | I12: =$D$4*(1+$D$7)^I10 -> 2.3346211e+11 | J12: =$D$4*(1+$D$7)^J10 -> 3.4804627e+11
D13: Terminal Value | J13: =J12/(D6-D5) -> 7.0974585e+11
D14: Total CF | E14: =E12 -> 4.7264396e+10 | F14: =F12 -> 7.0461955e+10 | G14: =G12 -> 1.0504497e+11 | H14: =H12 -> 1.5660147e+11 | I14: =I12+J13 -> 9.4320796e+11
D15: Equity Value (direct PV of FCFE) | E15: =NPV(D6,E14:I14)*(1+D6)^0.5 -> 3.0814399e+11
D17: Mkt securities | E17: 72922396635
D18: Financial lia. | E18: 5544840000
D19: Equity value | E19: =E15+E17-E18 -> 3.7552155e+11
D20: Stock Price | E20: =E19/D8 -> 71.6927

Sheet DDM
C3: DDM (Gordon Growth) Valuation
D4: Net Profit 2025 | E4: ='Income Statement-Robi'!E23 -> 9370822000 | H4: Perpetual growth rate | I4: 0.005
D5: Avg. Net Profit Growth | E5: ='Cost of Equity'!E7 -> 0.49080409 | H5: WACC | I5: =CFFA!H6 -> 0.26976351
D6: Dividends | E6: ='Cost of Equity'!E15 -> 8.38779e+08
D7: Dividend growth | E7: ='Cost of Equity'!O6 -> 0.175
D8: Total Shares | E8: ='FCFE Valuation'!D8 -> 5237932895
H11: 1 | I11: 2 | J11: 3 | K11: 4 | L11: 5 | M11: 6
G12: Year | H12: 2025 | I12: 2026 | J12: 2027 | K12: 2028 | L12: 2029 | M12: 2030
G13: Net profits | H13: =$E$4*(1+$E$5)^H11 -> 1.397006e+10 | I13: =$E$4*(1+$E$5)^I11 -> 2.0826622e+10 | J13: =$E$4*(1+$E$5)^J11 -> 3.1048413e+10 | K13: =$E$4*(1+$E$5)^K11 -> 4.6287102e+10 | L13: =$E$4*(1+$E$5)^L11 -> 6.9005001e+10 | M13: =$E$4*(1+$E$5)^M11 -> 1.0287294e+11
G14: Dividends | H14: =$E$6*(1+$E$7)^H11 -> 9.8556532e+08 | I14: =$E$6*(1+$E$7)^I11 -> 1.1580393e+09 | J14: =$E$6*(1+$E$7)^J11 -> 1.3606961e+09 | K14: =$E$6*(1+$E$7)^K11 -> 1.5988179e+09 | L14: =$E$6*(1+$E$7)^L11 -> 1.8786111e+09 | M14: =$E$6*(1+$E$7)^M11 -> 2.207368e+09
G15: Shares | H15: =E8 -> 5237932895 | I15: =E8 -> 5237932895 | J15: =E8 -> 5237932895 | K15: =E8 -> 5237932895 | L15: =E8 -> 5237932895 | M15: =E8 -> 5237932895
G16: Div/share | H16: =H14/H15 -> 0.18815921 | I16: =I14/I15 -> 0.22108707 | J16: =J14/J15 -> 0.25977731 | K16: =K14/K15 -> 0.30523834 | L16: =L14/L15 -> 0.35865505 | M16: =M14/M15 -> 0.42141968
G17: Terminal | M17: =M16/(I5-I4) -> 1.5916834
G18: Total CF | H18: =H16 -> 0.18815921 | I18: =I16 -> 0.22108707 | J18: =J16 -> 0.25977731 | K18: =K16 -> 0.30523834 | L18: =L16+M17 -> 1.9503385
G19: PV | H19: =NPV(I5,H18:L18)*(1+I5)^0.5 -> 1.2626196
